cmfsapy/__init__.py
cmfsapy/data.py
cmfsapy/theoretical.py
cmfsapy/__pycache__/__init__.cpython-37.pyc
cmfsapy/__pycache__/data.cpython-37.pyc
cmfsapy/__pycache__/theoretical.cpython-37.pyc
cmfsapy/dimension/__init__.py
cmfsapy/dimension/cmfsa.py
cmfsapy/dimension/correction.py
cmfsapy/dimension/fsa.py
cmfsapy/dimension/__pycache__/__init__.cpython-37.pyc
cmfsapy/dimension/__pycache__/cmfsa.cpython-37.pyc
cmfsapy/dimension/__pycache__/correction.cpython-37.pyc
cmfsapy/dimension/__pycache__/fsa.cpython-37.pyc
cmfsapy/evaluation/__init__.py
cmfsapy/evaluation/mpe.py
cmfsapy/evaluation/__pycache__/__init__.cpython-37.pyc
cmfsapy/evaluation/__pycache__/mpe.cpython-37.pyc
cmfsapy-0.0.0.dist-info/LICENSE
cmfsapy-0.0.0.dist-info/METADATA
cmfsapy-0.0.0.dist-info/WHEEL
cmfsapy-0.0.0.dist-info/top_level.txt
cmfsapy-0.0.0.dist-info/RECORD
